tkla_utils_flask_api/__init__.py
tkla_utils_flask_api/decorators.py
tkla_utils_flask_api/hashing.py
tkla_utils_flask_api/jwt_utils.py
tkla_utils_flask_api/responses.py
tkla_utils_flask_api/time_utils.py
tkla_utils_flask_api/tokens.py
tkla_utils_flask_api/version.py
tkla_utils_flask_api-0.1.0.dist-info/METADATA
tkla_utils_flask_api-0.1.0.dist-info/WHEEL
tkla_utils_flask_api-0.1.0.dist-info/top_level.txt
tkla_utils_flask_api-0.1.0.dist-info/RECORD
