Metadata-Version: 2.4
Name: tkla_utils_flask_api
Version: 0.1.0
Summary: JWT, hashing y utilidades para APIs Flask
Author: Lovenson Pierre
Classifier: Programming Language :: Python :: 3
Classifier: License :: OSI Approved :: MIT License
Classifier: Operating System :: OS Independent
Requires-Python: >=3.7
Requires-Dist: Flask
Requires-Dist: PyJWT
Requires-Dist: bcrypt
Dynamic: author
Dynamic: classifier
Dynamic: description
Dynamic: description-content-type
Dynamic: requires-dist
Dynamic: requires-python
Dynamic: summary
